[{"img":"../images/yuanchuang1.png","workType":"原创", "workTitle":"Sweet Pink |Blingking Light","workBody":"","imgInfo":"../images/shouye16.JPG","authorname":"Rosalyn"},{"img":"../images/shouye6.jpg","workType":"原创", "workTitle":"长乐林场记","workBody":"---","imgInfo":"../images/imgInfo2.jpg","authorname":"无限TX"},{"img":"../images/shouye1.jpg","workType":"杂志", "workTitle":"福岛县三岛町| 日本摄影师","workBody":"-","imgInfo":"../images/imgInfo1.jpg","authorname":"blank"},{"img":"../images/shouye15.jpg","workType":"原创", "workTitle":"Why iii Love The Moon","workBody":"关于为什么是3个i，看到一个回答，赞。--举杯邀明月，对影成三人","imgInfo":"../images/imgInfo6.jpg","authorname":"布鲁斯小岛"},{"img":"../images/shouye11.jpg","workType":"杂志", "workTitle":"Bruno Aveillan","workBody":"Bruno Aveillan,法国多媒体艺术家，摄影师，导演。他的作品承受着一种强大的张力和敏感的自然元素。","imgInfo":"../images/imgInfo7.jpg","authorname":"锦衣夜行"},{"img":"../images/5.jpg","workType":"原创", "workTitle":"劫后余生","workBody":"是温柔是留恋是时分历练的劫后余生","imgInfo":"../images/imgInfo8.jpg","authorname":"微醺十月"},{"img":"../images/6.jpg","workType":"杂志", "workTitle":"迷幻人像 | Jennifer Medina","workBody":"Jennifer Medina","imgInfo":"../images/imgInfo1.jpg","authorname":"blank"},{"img":"../images/7.jpg","workType":"原创", "workTitle":"Nightfall","workBody":"-","imgInfo":"../images/imgInfo9.jpg","authorname":"梦境记录册"},{"img":"../images/shouye4.jpg","workType":"杂志", "workTitle":"夏永康作品赏析","workBody":"夏永康（Wing Shya），出生於1964年，香港攝影師、設計師、導演，張國榮御用攝影師，曾參與王家衛《花樣年華》、《春光乍泄》","imgInfo":"../images/imgInfo7.jpg","authorname":"锦衣夜行"},{"img":"../images/shouye3.jpg","workType":"原创", "workTitle":"WHITE NOISE","workBody":"@ARRIFLEX KODAK VISION3 500T","imgInfo":"../images/imgInfo4.jpg","authorname":"iBiscuit"}
]




